{
  "DbConnection": {
    "DataBase": "PostgreSQL",
    "NotifyConnectionString": "host=localhost;port=5432;Database=NotificationsExchangeClients;Username=postgres;Password=19346jaidj",
    "AlarmConnectionString": "host=localhost;port=5432;Database=AlarmsExchangeClients;Username=postgres;Password=19346jaidj"
  },
  "ClientSettings": {
    "ClientId": "16067fbc-14e9-4d0c-aa4c-cfcf5246a133",
    "UseCache": true
  },
  "ConnectionSettings": {
    "NotifyUrl": "https://localhost:8080/hubs/NotificationHub/Send",
    "AlarmUrl": "https://localhost:8080/hubs/AlarmHub/Send"
  }
}